textx_gen_coloring/__init__.py
textx_gen_coloring/generators.py
textx_gen_coloring/metamodels/__init__.py
textx_gen_coloring/metamodels/coloring.tx
textx_gen_coloring/templates/__init__.py
textx_gen_coloring/templates/textmate/language.json.template
textx_gen_coloring-0.2.0.dist-info/entry_points.txt
textx_gen_coloring-0.2.0.dist-info/licenses/LICENSE
textx_gen_coloring-0.2.0.dist-info/WHEEL
textx_gen_coloring-0.2.0.dist-info/METADATA
textx_gen_coloring-0.2.0.dist-info/RECORD
